marmopy/__init__.py
marmopy/conf.py
marmopy/constants.py
marmopy/intent.py
marmopy/intent_action.py
marmopy/provider.py
marmopy/utils.py
marmopy/wallet.py
marmopy/builders/ERC20.py
marmopy/builders/ETH.py
marmopy/builders/__init__.py
marmopy/builders/contract.py
marmopy-0.3.1.dist-info/METADATA
marmopy-0.3.1.dist-info/WHEEL
marmopy-0.3.1.dist-info/top_level.txt
marmopy-0.3.1.dist-info/RECORD
